LICENSE
README.md
setup.py
baijudodhia_toolkit_py.egg-info/PKG-INFO
baijudodhia_toolkit_py.egg-info/SOURCES.txt
baijudodhia_toolkit_py.egg-info/dependency_links.txt
baijudodhia_toolkit_py.egg-info/requires.txt
baijudodhia_toolkit_py.egg-info/top_level.txt
tests/__init__.py
tests/test_condition.py
tests/test_rule.py
tests/test_source.py
toolkit/__init__.py
toolkit/chakra/__init__.py
toolkit/chakra/action.py
toolkit/chakra/condition.py
toolkit/chakra/engine.py
toolkit/chakra/formula.py
toolkit/chakra/patterns.py
toolkit/chakra/rule.py
toolkit/chakra/source.py