Metadata-Version: 2.1
Name: baijudodhia-toolkit-py
Version: 0.1.2
Summary: A Simple to Integrate Python Rule Engine based on JSON Configuration
Home-page: https://github.com/baijudodhia/toolkit-py
Author: Baiju Dodhia
License: UNKNOWN
Platform: UNKNOWN
Classifier: Programming Language :: Python :: 3
Classifier: License :: OSI Approved :: MIT License
Classifier: Operating System :: OS Independent
